[
  {
    "id": "1",
    "name": "Augusta National Golf Club",
    "location": "Augusta, Georgia",
    "courseRating": 75.1,
    "slopeRating": 137,
    "holes": [
      {
        "number": 1,
        "par": 4,
        "yardage": 445,
        "teeBox": {"latitude": 33.5035, "longitude": -82.0209},
        "green": {
          "front": {"latitude": 33.5061, "longitude": -82.0213},
          "center": {"latitude": 33.5062, "longitude": -82.0212},
          "back": {"latitude": 33.5063, "longitude": -82.0211}
        }
      },
      {
        "number": 2,
        "par": 5,
        "yardage": 575,
        "teeBox": {"latitude": 33.5067, "longitude": -82.0218},
        "green": {
          "front": {"latitude": 33.5088, "longitude": -82.0221},
          "center": {"latitude": 33.5089, "longitude": -82.0220},
          "back": {"latitude": 33.5090, "longitude": -82.0219}
        }
      },
      {
        "number": 3,
        "par": 4,
        "yardage": 350,
        "teeBox": {"latitude": 33.5095, "longitude": -82.0224},
        "green": {
          "front": {"latitude": 33.5112, "longitude": -82.0226},
          "center": {"latitude": 33.5113, "longitude": -82.0225},
          "back": {"latitude": 33.5114, "longitude": -82.0224}
        }
      }
    ]
  }
]

